tile_stitch/__init__.py
tile_stitch/__main__.py
tile_stitch/tile_stitch.py
tile_stitch/version.py
tile_stitch-0.0.0.dist-info/METADATA
tile_stitch-0.0.0.dist-info/WHEEL
tile_stitch-0.0.0.dist-info/top_level.txt
tile_stitch-0.0.0.dist-info/RECORD
