Metadata-Version: 2.1
Name: tile_stitch
Version: 0.0.0
Summary: blends images using three different methods
Home-page: https://github.com/jucik/tile_stitch
Author: jucik
Classifier: Programming Language :: Python :: 3
Classifier: License :: OSI Approved :: MIT License
Classifier: Operating System :: OS Independent
Classifier: Topic :: Scientific/Engineering :: Image Processing
Requires-Python: >=3.6
